jet_django/__init__.py
jet_django/apps.py
jet_django/configuration.py
jet_django/route_view.py
jet_django/router.py
jet_django/settings.py
jet_django/urls.py
jet_django/__pycache__/__init__.cpython-36.pyc
jet_django/migrations/0001_initial.py
jet_django/migrations/0002_auto_20181014_2002.py
jet_django/migrations/0003_auto_20191007_2005.py
jet_django/migrations/__init__.py
jet_django-1.12.7.dist-info/LICENSE
jet_django-1.12.7.dist-info/METADATA
jet_django-1.12.7.dist-info/WHEEL
jet_django-1.12.7.dist-info/top_level.txt
jet_django-1.12.7.dist-info/RECORD
