Metadata-Version: 2.1
Name: jet-django
Version: 1.12.7
Summary: UNKNOWN
Home-page: https://github.com/jet-admin/jet-django
Author: Denis Kildishev
Author-email: hello@geex-arts.com
License: MIT
Platform: UNKNOWN
Requires-Dist: Django
Requires-Dist: requests
Requires-Dist: jet-bridge-base (==1.12.7)
